{
  "id": "eon-rpg",
  "title": "Eon IV RPG",
  "version": "2.0.4",
  "compatibility": {
    "minimum": "11",
    "verified": "11",
    "maximum": "11"
  },
  "authors": [
    {
      "name": "Johan Fält",
      "discord": "johanfk#0054",
      "flags": {}
    }
  ],
  "esmodules": [
    "module/eon-rpg.js"
  ],
  "styles": [
    "styles/eon-main.css",
    "styles/editor/editor.css"
  ],
  "relationships": {
    "requires": [
      {
        "id": "eon-dice-roller",
        "type": "module",
        "manifest": "https://raw.githubusercontent.com/JohanFalt/Foundry_EonDiceRoller/main/module.json",
        "compatibility": {
          "minimum": "1.6.0",
          "verified": "1.6.0",
          "maximum": "2"
        }
      }
    ]
  },
  "initiative": "@harleddegenskaper.initiativ.tarning + @harleddegenskaper.initiativ.bonus",
  "gridDistance": 2,
  "gridUnits": "m",
  "url": "https://github.com/JohanFalt/Foundry_EON-RPG",
  "manifest": "https://raw.githubusercontent.com/JohanFalt/Foundry_EON-RPG/main/system.json",
  "download": "https://github.com/JohanFalt/Foundry_EON-RPG/archive/refs/tags/2.0.4.zip",
  "bugs": "https://github.com/JohanFalt/Foundry_EON-RPG/issues",
  "license": "LICENSE.txt"
}